common
rangermodels
servicefinder
serviceprovider
