Metadata-Version: 2.1
Name: python-ranger-tn
Version: 1.8.3
Summary: The python equivalent for ranger based service discovery mechanism using zookeeper
Home-page: https://github.com/Tushar-Naik/python-ranger-daemon
Author: Tushar Naik
Author-email: tushar.knaik@gmail.com
License:  License 2.0
Keywords: ranger,zookeeper,service discovery,periodic task,interval,periodic job,flask style,decorator,tushar
Platform: UNKNOWN
Classifier: Development Status :: 5 - Production/Stable
Classifier: Intended Audience :: Developers
Classifier: License :: OSI Approved :: Apache Software License
Classifier: Operating System :: OS Independent
Classifier: Programming Language :: Python :: 3.9
Classifier: Programming Language :: Python :: Implementation :: PyPy
Classifier: Topic :: Utilities
Classifier: Topic :: System :: Networking
Classifier: Topic :: System :: Distributed Computing
License-File: LICENCE
